jasminum-0.3.5.dist-info/METADATA
jasminum-0.3.5.dist-info/WHEEL
jasminum-0.3.5.dist-info/entry_points.txt
jasminum-0.3.5.dist-info/licenses/LICENSE
jasminum/ast.py
jasminum/cfg.py
jasminum/constant.py
jasminum/context.py
jasminum/debug.py
jasminum/df.py
jasminum/engine.py
jasminum/eval.py
jasminum/exceptions.py
jasminum/expr.py
jasminum/history_console.py
jasminum/io.py
jasminum/iterator.py
jasminum/j.py
jasminum/j_conn.py
jasminum/j_fn.py
jasminum/j_handle.py
jasminum/j_task.py
jasminum/main.py
jasminum/math.py
jasminum/operator.py
jasminum/other.py
jasminum/partitioned_df.py
jasminum/serde.py
jasminum/series.py
jasminum/sql.py
jasminum/string.py
jasminum/temporal.py
jasminum/util.py
jasminum/__init__.py
rust-toolchain.toml
jasminum/jasminum.cp313-win_amd64.pyd
jasminum-0.3.5.dist-info/RECORD
