Metadata-Version: 2.4
Name: jasminum
Version: 0.3.5
Classifier: Programming Language :: Python :: 3
Classifier: Programming Language :: Python :: 3 :: Only
Classifier: Programming Language :: Python :: 3.11
Classifier: Programming Language :: Python :: 3.12
Classifier: Programming Language :: Python :: 3.13
Classifier: Programming Language :: Rust
Requires-Dist: polars >=1.18.0
Requires-Dist: pyarrow >=18.0.0
Requires-Dist: termcolor >=2.5.0
Requires-Dist: numpy >=2.2.0
Requires-Dist: duckdb >=1.1.0 ; extra == 'duckdb'
Provides-Extra: duckdb
License-File: LICENSE
Summary: an implementation of the data analytics programming language jasmine
Keywords: jasmine,jasminum,polars,dataframe,arrow
Author: the Jasmine authors
Requires-Python: >=3.11
Project-URL: Repository, https://github.com/hinmeru/jasmine
